abide_data_explorer/__init__.py
abide_data_explorer/app.py
abide_data_explorer/cli.py
abide_data_explorer/data/sample_data.csv
abide_data_explorer-1.0.0.dist-info/licenses/LICENSE
abide_data_explorer-1.0.0.dist-info/METADATA
abide_data_explorer-1.0.0.dist-info/WHEEL
abide_data_explorer-1.0.0.dist-info/entry_points.txt
abide_data_explorer-1.0.0.dist-info/top_level.txt
abide_data_explorer-1.0.0.dist-info/RECORD
