Metadata-Version: 2.4
Name: abide-data-explorer
Version: 1.0.0
Summary: A Streamlit application for exploring ABIDE II Composite Phenotypic data
Home-page: https://github.com/ItsHarshitAg/lab10
Author: Data Explorer Team
Author-email: contact@example.com
Project-URL: Bug Reports, https://github.com/yourusername/abide-data-explorer/issues
Project-URL: Source, https://github.com/yourusername/abide-data-explorer
Keywords: data analysis,streamlit,abide,neuroscience,visualization
Classifier: Development Status :: 4 - Beta
Classifier: Intended Audience :: Science/Research
Classifier: Topic :: Scientific/Engineering :: Bio-Informatics
Classifier: License :: OSI Approved :: MIT License
Classifier: Programming Language :: Python :: 3
Classifier: Programming Language :: Python :: 3.7
Classifier: Programming Language :: Python :: 3.8
Classifier: Programming Language :: Python :: 3.9
Classifier: Programming Language :: Python :: 3.10
Classifier: Programming Language :: Python :: 3.11
Requires-Python: >=3.7
License-File: LICENSE
Requires-Dist: streamlit>=1.28.0
Requires-Dist: pandas>=1.3.0
Requires-Dist: numpy>=1.21.0
Requires-Dist: plotly>=5.0.0
Requires-Dist: matplotlib>=3.5.0
Requires-Dist: openpyxl>=3.0.0
Dynamic: author
Dynamic: author-email
Dynamic: classifier
Dynamic: description
Dynamic: description-content-type
Dynamic: home-page
Dynamic: keywords
Dynamic: license-file
Dynamic: project-url
Dynamic: requires-dist
Dynamic: requires-python
Dynamic: summary
